[
  {
    "ContainingType": "Blog_Backend.Controllers.AuthController",
    "Method": "Login",
    "RelativePath": "api/Auth/login",
    "HttpMethod": "POST",
    "IsController": true,
    "Order": 0,
    "Parameters": [
      {
        "Name": "loginDTO",
        "Type": "Blog_Backend.DTO.LoginDTO",
        "IsRequired": true
      }
    ],
    "ReturnTypes": []
  },
  {
    "ContainingType": "Blog_Backend.Controllers.AuthController",
    "Method": "Register",
    "RelativePath": "api/Auth/register",
    "HttpMethod": "POST",
    "IsController": true,
    "Order": 0,
    "Parameters": [
      {
        "Name": "registerDTO",
        "Type": "Blog_Backend.DTO.RegisterDTO",
        "IsRequired": true
      }
    ],
    "ReturnTypes": []
  },
  {
    "ContainingType": "Blog_Backend.Controllers.BlogController",
    "Method": "GetAllBlogs",
    "RelativePath": "api/Blog/allBlogs",
    "HttpMethod": "GET",
    "IsController": true,
    "Order": 0,
    "Parameters": [],
    "ReturnTypes": [
      {
        "Type": "System.Collections.Generic.IEnumerable\u00601[[BlogDTO, Blog-Backend, Version=1.0.0.0, Culture=neutral, PublicKeyToken=null]]",
        "MediaTypes": [
          "text/plain",
          "application/json",
          "text/json"
        ],
        "StatusCode": 200
      }
    ]
  },
  {
    "ContainingType": "Blog_Backend.Controllers.BlogController",
    "Method": "CreateBlog",
    "RelativePath": "api/Blog/createBlog",
    "HttpMethod": "POST",
    "IsController": true,
    "Order": 0,
    "Parameters": [
      {
        "Name": "createBlogDTO",
        "Type": "Blog_Backend.DTO.CreateBlogDTO",
        "IsRequired": true
      }
    ],
    "ReturnTypes": [
      {
        "Type": "Blog_Backend.Models.Blog",
        "MediaTypes": [
          "text/plain",
          "application/json",
          "text/json"
        ],
        "StatusCode": 200
      }
    ]
  },
  {
    "ContainingType": "Blog_Backend.Controllers.BlogController",
    "Method": "DeleteBlog",
    "RelativePath": "api/Blog/deleteBlog/{id}",
    "HttpMethod": "PUT",
    "IsController": true,
    "Order": 0,
    "Parameters": [
      {
        "Name": "id",
        "Type": "System.Int32",
        "IsRequired": true
      }
    ],
    "ReturnTypes": []
  },
  {
    "ContainingType": "Blog_Backend.Controllers.BlogController",
    "Method": "GetMyBlogs",
    "RelativePath": "api/Blog/myBlogs",
    "HttpMethod": "GET",
    "IsController": true,
    "Order": 0,
    "Parameters": [],
    "ReturnTypes": [
      {
        "Type": "System.Collections.Generic.IEnumerable\u00601[[BlogDTO, Blog-Backend, Version=1.0.0.0, Culture=neutral, PublicKeyToken=null]]",
        "MediaTypes": [
          "text/plain",
          "application/json",
          "text/json"
        ],
        "StatusCode": 200
      }
    ]
  },
  {
    "ContainingType": "Blog_Backend.Controllers.BlogController",
    "Method": "UpdateBlog",
    "RelativePath": "api/Blog/updateBlog/{id}",
    "HttpMethod": "PUT",
    "IsController": true,
    "Order": 0,
    "Parameters": [
      {
        "Name": "id",
        "Type": "System.Int32",
        "IsRequired": true
      },
      {
        "Name": "updateBlogDTO",
        "Type": "UpdateBlogDTO",
        "IsRequired": true
      }
    ],
    "ReturnTypes": []
  },
  {
    "ContainingType": "Blog_Backend.Controllers.BlogController",
    "Method": "GetBlog",
    "RelativePath": "api/Blog/viewBlog/{id}",
    "HttpMethod": "GET",
    "IsController": true,
    "Order": 0,
    "Parameters": [
      {
        "Name": "id",
        "Type": "System.Int32",
        "IsRequired": true
      }
    ],
    "ReturnTypes": [
      {
        "Type": "BlogDTO",
        "MediaTypes": [
          "text/plain",
          "application/json",
          "text/json"
        ],
        "StatusCode": 200
      }
    ]
  },
  {
    "ContainingType": "Blog_Backend.Controllers.ReaderController",
    "Method": "DeleteReader",
    "RelativePath": "api/Reader/delete/{readerId}",
    "HttpMethod": "PUT",
    "IsController": true,
    "Order": 0,
    "Parameters": [
      {
        "Name": "readerId",
        "Type": "System.Int32",
        "IsRequired": true
      }
    ],
    "ReturnTypes": []
  },
  {
    "ContainingType": "Blog_Backend.Controllers.ReaderController",
    "Method": "GetAllReaders",
    "RelativePath": "api/Reader/getAll",
    "HttpMethod": "GET",
    "IsController": true,
    "Order": 0,
    "Parameters": [],
    "ReturnTypes": [
      {
        "Type": "System.Collections.Generic.IEnumerable\u00601[[Blog_Backend.DTO.ReaderDTO, Blog-Backend, Version=1.0.0.0, Culture=neutral, PublicKeyToken=null]]",
        "MediaTypes": [
          "text/plain",
          "application/json",
          "text/json"
        ],
        "StatusCode": 200
      }
    ]
  },
  {
    "ContainingType": "Blog_Backend.Controllers.ReaderController",
    "Method": "GetCurrentReader",
    "RelativePath": "api/Reader/getCurrentReader",
    "HttpMethod": "GET",
    "IsController": true,
    "Order": 0,
    "Parameters": [],
    "ReturnTypes": []
  },
  {
    "ContainingType": "Blog_Backend.Controllers.ReaderController",
    "Method": "GetReaderById",
    "RelativePath": "api/Reader/getReader/{id}",
    "HttpMethod": "GET",
    "IsController": true,
    "Order": 0,
    "Parameters": [
      {
        "Name": "id",
        "Type": "System.Int32",
        "IsRequired": true
      }
    ],
    "ReturnTypes": [
      {
        "Type": "Blog_Backend.DTO.ReaderDTO",
        "MediaTypes": [
          "text/plain",
          "application/json",
          "text/json"
        ],
        "StatusCode": 200
      }
    ]
  },
  {
    "ContainingType": "Blog_Backend.Controllers.ReaderController",
    "Method": "UpdateEmail",
    "RelativePath": "api/Reader/updateEmail",
    "HttpMethod": "PUT",
    "IsController": true,
    "Order": 0,
    "Parameters": [
      {
        "Name": "updateEmailDTO",
        "Type": "UpdateEmailDTO",
        "IsRequired": true
      }
    ],
    "ReturnTypes": []
  },
  {
    "ContainingType": "Blog_Backend.Controllers.ReaderController",
    "Method": "UpdateProfile",
    "RelativePath": "api/Reader/updateProfile",
    "HttpMethod": "PUT",
    "IsController": true,
    "Order": 0,
    "Parameters": [
      {
        "Name": "updateReaderDTO",
        "Type": "Blog_Backend.DTO.UpdateReaderDTO",
        "IsRequired": true
      }
    ],
    "ReturnTypes": []
  },
  {
    "ContainingType": "Program\u002B\u003C\u003Ec__DisplayClass0_0",
    "Method": "\u003C\u003CMain\u003E$\u003Eb__7",
    "RelativePath": "weatherforecast",
    "HttpMethod": "GET",
    "IsController": false,
    "Order": 0,
    "Parameters": [],
    "ReturnTypes": [
      {
        "Type": "WeatherForecast[]",
        "MediaTypes": [
          "application/json"
        ],
        "StatusCode": 200
      }
    ],
    "EndpointName": "GetWeatherForecast"
  }
]